[{"videoId":"Q8aqUuQlx0Q","title":"3426 - الأحوال التي يجوز فيها الكذب - نور على الدرب","position":0},{"videoId":"h4fNtFo3W_A","title":"3434 - توجيه لمن يشعر بالخجل عند ملاقاة الناس  - نور على الدرب","position":1},{"videoId":"hWyyJkV1O1k","title":"3454 - صفة الأفراح الموافقة للشرع - نور على الدرب","position":2},{"videoId":"IH7MIbIrKfM","title":"3467 - حكم استماع المرأة القرآن أثناء تأدية أعمال البيت - نور على الدرب","position":3},{"videoId":"w1FPLHKx_M0","title":"3484 - الوصية بالوالدين والإحسان إليهما - نور على الدرب","position":4},{"videoId":"t8OnnOiErR8","title":"3502 - حكم العيش مع من لا يصلي ولا يصوم  - نور على الدرب","position":5},{"videoId":"unN3RBso5S4","title":"3553 - حكم الجلوس بين أناس لا يتورعون عن الخوض في أعراض الناس - نور على الدرب","position":6},{"videoId":"iRIir17Dp-c","title":"3564 - حكم من أهدى لوالدته ذهباً ثم أخذه منها لحاجته إليه - نور على الدرب","position":7},{"videoId":"yMJ-XklD1_c","title":"3574 - حكم الغش في الامتحانات - نور على الدرب","position":8},{"videoId":"OFNF_4q8bE4","title":"3638 - حكم شكر الإنسان على الإحسان - نور على الدرب","position":9},{"videoId":"Gq_aDfcXv5s","title":"3639 - حكم قول القائل بعد الاستخارة (إن الله قد اختار لي هذا الأمر) - نور على الدرب","position":10},{"videoId":"6qWHMEgB7Gw","title":"3643 - حكم صلة القريب العاصي  - نور على الدرب","position":11},{"videoId":"WHy0I0sBOsA","title":"3673 - حكم استعمال الحناء للرجل - نور على الدرب","position":12},{"videoId":"0HT8uP8EIkQ","title":"3710 - حكم مبيت الرجل عند إحدى أخواته  - نور على الدرب","position":13},{"videoId":"nV7q7dgzz-M","title":"3711 - حكم مبيت الأخت في بيت زوج أختها  - نور على الدرب","position":14},{"videoId":"LZM__nyzh0g","title":"3744 - حكم هجر القرابة الذين يشتغلون بالغيبة والنميمة في مجالسهم  - نور على الدرب","position":15},{"videoId":"1uN19mEG-6E","title":"3759 - حكم مرور الطفل بين يدي المصلي - نور على الدرب","position":16},{"videoId":"4VPEFwmu_vI","title":"3769 - حكم قتل الهرة من غير عمد  - نور على الدرب","position":17},{"videoId":"3icthFVqQQ8","title":"3770   حكم الكذب لرد المدين المماطل   نور على الدرب","position":18},{"videoId":"ad0PelLPVKQ","title":"3771   الترهيب من المماطلة في أداء الديون لأصحابها   نور على الدرب","position":19},{"videoId":"nRl9F0yLSWE","title":"3772   ابتلاء المسلم في الدنيا وفضل الصبر على ذلك   نور على الدرب","position":20},{"videoId":"-bCGhHwbz14","title":"3821   حكم رمي الأظفار والشعر في سلة المهملات    نور على الدرب","position":21},{"videoId":"cKdjgOdFtrQ","title":"3857 - حكم اختلاط النساء بالرجال في الأعراس - نور على الدرب","position":22},{"videoId":"XPHoivqmzWA","title":"3862 - كيفية معالجة مشاكل الأم مع أبنائها وزوجاتهم - نور على الدرب","position":23},{"videoId":"6iPRWv4Ns4w","title":"3873 - حكم المزاح والإكثار منه - نور على الدرب","position":24},{"videoId":"qUYOGsqBIZo","title":"3875 - حكم التدخين وأضراره - نور على الدرب","position":25},{"videoId":"aaPuX-5PO50","title":"3949 - حكم إلقاء قلامة الأظافر والشعر في القمامة - نور على الدرب","position":26},{"videoId":"wrgcrljMowg","title":"3994 - حكم مبيت المرأة في بيت زوج أختها - نور على الدرب","position":27},{"videoId":"1cdQ2PSBfi8","title":"4003 - حكم من أفتى بما سمعه من برنامج نور على الدرب - نور على الدرب","position":28},{"videoId":"D5-1tk07uEM","title":"4004 - حكم كتابة بحث لطالب ليقدمه على أنه من جهده  - نور على الدرب","position":29},{"videoId":"N5NHxqAHlmA","title":"4005 - حرمان القريب من المعروف المادي لتركه الصلاة - نور على الدرب","position":30},{"videoId":"m0WiAPEwXiw","title":"4042 - حكم التسمي بالأثري  - نور على الدرب","position":31},{"videoId":"mmxvK2A4qI4","title":"4123 - حكم قطيعة الرحم بسبب أذيتهم  - نور على الدرب","position":32},{"videoId":"cwFl8Xaf4e0","title":"4136 - حكم أخذ أي شيء من بيت الأب بدون علمه - نور على الدرب","position":33},{"videoId":"g9Ln6SWqjZQ","title":"4140 - واجب أم الزوجة وقريباتها تجاه الزوجين  - نور على الدرب","position":34},{"videoId":"AOUGNlWAQNo","title":"4189 - حكم الوالد الذي لا يأمر أولاده بالصلاة - نور على الدرب","position":35},{"videoId":"MlcLddkMs3o","title":"4235 -  حكم إعلام الشخص من اغتابهم للتحلل منهم - نور على الدرب","position":36},{"videoId":"LtdZVVbRp5I","title":"4281 -  حكم الزيارة التي تؤدي إلى الوقوع في الغيبة والنميمة - نور على الدرب","position":37},{"videoId":"Z21l3zpmjH4","title":"4293 -  مدى صحة قول (لعن الشارب قبل الطالب)  - نور على الدرب","position":38},{"videoId":"5pDSzsV76YI","title":"4294 -  علاج الوساوس والشكوك - نور على الدرب","position":39},{"videoId":"Hoq2QHSqOR0","title":"4296 -  حكم صلة الأرحام الذين لا يرحبون بالزيارة  - نور على الدرب","position":40},{"videoId":"v6oGvBx-qgU","title":"4317 -  كيفية التخلص من وساوس الشيطان - نور على الدرب","position":41},{"videoId":"daD8i1ZkEi4","title":"4318 -  كيفية نصيحة الأم التي تتلفظ بألفاظ غير لائقة - نور على الدرب","position":42},{"videoId":"AeOvjmHpN6w","title":"4319 -  واجب من أساء إلى الجيران وتاب من ذلك - نور على الدرب","position":43},{"videoId":"T4PipiIiXuo","title":"4333 -  حكم كشف المرأة وجهها - نور على الدرب","position":44},{"videoId":"MDllotXzd5k","title":"4334 -  حكم صوت المرأة ومصافحتها للرجال - نور على الدرب","position":45},{"videoId":"lTfj7pkabtE","title":"4340 -  حكم تعليق الآيات القرآنية على الجدران  - نور على الدرب","position":46},{"videoId":"1wYnoVTvgGs","title":"4353 -  حكم جلسة الاستراحة ووضع اليد اليمنى على اليسرى في الصلاة - نور على الدرب","position":47},{"videoId":"3yM9mGqihUw","title":"4414 -  توجيه لمن يشعر بالخجل عند ملاقاة الناس - نور على الدرب","position":48},{"videoId":"wDZ0s-gPV8o","title":"4481 -  حكم النحنحة والسعال في الصلاة للحاجة - نور على الدرب","position":49},{"videoId":"fF4A8Qcmr1Q","title":"4506 -  ضابط قبول فتوى المفتي والرضا بها - نور على الدرب","position":50},{"videoId":"yNoqCATGUnE","title":"4581 -  حكم تربية الكلاب - نور على الدرب","position":51},{"videoId":"MkdvN6iT05g","title":"4783 -  أحكام اللقطة وأنواعها - نور على الدرب","position":52},{"videoId":"ibu_fdF5Ltk","title":"4871 -  حكم الأكل مما يسقط من ثمر النخيل - نور على الدرب","position":53},{"videoId":"6I0aKoQv0Wk","title":"5114 -  حكم كتابة الآيات والأحاديث على الجدران- نور على الدرب","position":54},{"videoId":"DOuWmGHpZ70","title":"5138 -   حكم الأكل من طعام تارك الصلاة والاقتراض منه  - نور على الدرب","position":55},{"videoId":"efTULiEofgo","title":"5148 -   نصيحة لمن ابتلي بالكذب وغيبة المسلمين- نور على الدرب","position":56},{"videoId":"bn8UY3A8fqA","title":"5198 - حكم صلة الأقارب الذين لا يؤدون الصلة - نور على الدرب","position":57},{"videoId":"FL_mbjGu_ZY","title":"5219 -  حكم مصافحة الأجنبية كبيرة السن - نور على الدرب","position":58},{"videoId":"YseJRBp9Tpk","title":"5241 -  عدم ثبوت صلاة لماء زمزم  - نور على الدرب","position":59},{"videoId":"_Slf9utfX2Y","title":"5248 -  إيصال ثواب الأعمال إلى البيت - نور على الدرب","position":60},{"videoId":"UIxn0yAcMUE","title":"5255 -  حكم إلقاء السلام على تارك الصلاة - نور على الدرب","position":61},{"videoId":"KCiVxp-pGpo","title":"5258 -  كيفية معالجة الحقد والحسد - نور على الدرب","position":62},{"videoId":"kuYgIi3HBPM","title":"5259 -  الحرص على عدم نسيان القرآن الكريم بعد حفظه - نور على الدرب","position":63},{"videoId":"2fA6B6dDtBk","title":"5260 - وجوب حفظ اللسان  - نور على الدرب","position":64},{"videoId":"lgml-E4dx-Q","title":"5269 - حكم تقبيل أيدي الوالدين - نور على الدرب","position":65},{"videoId":"zeV39UE9Hvc","title":"5295 - حكم المداومة على المصافحة بعد الفرائض   - نور على الدرب","position":66},{"videoId":"rKeNkTBfibI","title":"5331 - علاج الوسوسة والنسيان في الصلاة  - نور على الدرب","position":67},{"videoId":"HBm5CjDOOog","title":"5375 -  حكم غض البصر - نور على الدرب","position":68},{"videoId":"bnp9E05Ozzc","title":"5399 -   حكم قطع الأشجار للمصلحة - نور على الدرب","position":69},{"videoId":"O2PAemTeluM","title":"5418 -  البدء بالسلام عند المكالمة بالهاتف بين الرجل والمرأة - نور على الدرب","position":70},{"videoId":"CTnXdv6FMN0","title":"5422 -  حكم حبس الطيور في الأقفاص  - نور على الدرب","position":71},{"videoId":"WsFpTMA6iCY","title":"5430 -   حكم الدخان وإيذاء المصلين برائحته  - نور على الدرب","position":72},{"videoId":"2PNRuLvyerM","title":"5438 - حكم المراسلة بين الخطيبين  - نور على الدرب","position":73},{"videoId":"6HC3bjjGQUM","title":"5484 -   حكم خروج المحادة من بيتها لغير ضرورة  - نور على الدرب","position":74},{"videoId":"9UtpojHtnSk","title":"5491 -   حكم تقبيل الرجل محارمه في الوجه - نور على الدرب","position":75},{"videoId":"FozEUOcLi7E","title":"5515 - حكم رمي وامتهان الأوراق التي فيها ذكر الله  - نور على الدرب","position":76},{"videoId":"LbAg9CuF28w","title":"5529 - حكم التسبيح بالسبحة  - نور على الدرب","position":77},{"videoId":"XISjnLr5fqI","title":"5550 -  حكم مصافحة المرأة الأجنبية الكبيرة في السن  - نور على الدرب","position":78},{"videoId":"I_F0Lw7W2aU","title":"5574 -  حكم قبول الهدايا ممن ماله مكتسب من طريق الحلال والحرام  - نور على الدرب","position":79},{"videoId":"cGPlnX46Gew","title":"5628 -  وجوب الحذر من سوء الظن - نور على الدرب","position":80},{"videoId":"fYiZTBJHU4o","title":"5629 -  وجوب الاهتمام بالأبناء وتربيتهم التربية الإيمانية - نور على الدرب","position":81},{"videoId":"H4I1qWvY8cg","title":"5630 -  حكم ألعاب الأطفال المجسمة  - نور على الدرب","position":82},{"videoId":"FtwOl0mBtbY","title":"5633 -  حكم التشاؤم بالعين إذا رفت  - نور على الدرب","position":83},{"videoId":"WuxooFtCC50","title":"5634 -  ضرورة الابتعاد عن التعصب والغضب عند النقاش  - نور على الدرب","position":84},{"videoId":"jMHOYhdVK_8","title":"5645 -  كيفية صلة الرحم - نور على الدرب","position":85},{"videoId":"YUPB7YkiPe0","title":"5647 -  الآداب التي ينبغي أن يتحلى بها سائقو السيارات - نور على الدرب","position":86},{"videoId":"2CUqcPGJFng","title":"5648 -  تساهل الكثير من الناس باللعان والشتائم - نور على الدرب","position":87},{"videoId":"2dOBQLLw5Lc","title":"5686 -  حكم إكرام الضيف التارك للصلاة - نور على الدرب","position":88},{"videoId":"rcB29KlUWsc","title":"5692 -  حكم إكرامية الأجير على عمله  - نور على الدرب","position":89},{"videoId":"AWTsCU3TPDY","title":"5694 -  من صور الوعد  - نور على الدرب","position":90},{"videoId":"xxuEl_TjFlI","title":"5798 -  السن الذي يؤدب فيه الطفل إذا ارتكب خطأ - نور على الدرب","position":91},{"videoId":"w219N-NJuak","title":"5825 -  وسائل دفع الوساوس في الصلاة - نور على الدرب","position":92},{"videoId":"5RUfV6-YC7c","title":"5951 - حقيقة الزهد في الدنيا  - نور على الدرب","position":93},{"videoId":"kp6tYLNyJpI","title":"6014 - علامات قبول الله لأعمال العبد ورضاه عنه  - نور على الدرب","position":94},{"videoId":"Mwr05lUsuvg","title":"6031 - حكم مخالطة الجار تارك الصلاة والزكاة - نور على الدرب","position":95},{"videoId":"PBVxCEIfOSc","title":"6093 -  ضابط النميمة ونصيحة النمام - نور على الدرب","position":96},{"videoId":"JQ9fV9IAJY0","title":"6094 -  الضابط في معرفة الإسراف والتبذير - نور على الدرب","position":97},{"videoId":"rH99ylDYm6c","title":"6112 -  البلاء بالمسلم بين التكفير ورفع الدرجات وعاقبة الذنوب - نور على الدرب","position":98},{"videoId":"3WXv7xTLU-A","title":"6136 -  حكم منع الرجل زوجته من زيارة بيت والدها  - نور على الدرب","position":99},{"videoId":"MchLVmJEa-g","title":"6144 -  حكم جلوس الخطيب مع مخطوبته بحضور أمها أو أختها  - نور على الدرب","position":100},{"videoId":"bEOYlJ2tAn4","title":"6147 -  واجب المربين والمعلمين تجاه طلابهم - نور على الدرب","position":101},{"videoId":"uSlzMmO3bQw","title":"6154 -  حكم كراهية الغيبة بالقلب دون اللسان  - نور على الدرب","position":102},{"videoId":"Vse-8P-47ug","title":"6212 - مشروعية قراءة القرآن لكل إنسان على كل حال وهيئة ما لم يكن جنباً  - نور على الدرب","position":103},{"videoId":"o2ZJ51mKeQY","title":"6213 - حكم من ذبح هرة للشك في أذيتها - نور على الدرب","position":104},{"videoId":"4VqF_IXDUYs","title":"6223 - حكم هجر تارك الصلاة إذا نصح ولم ينفع معه - نور على الدرب","position":105},{"videoId":"RBFMhTIxXR0","title":"6245 - حكم هجر الأخت لأخواتها بسبب سوء أخلاقهن - نور على الدرب","position":106},{"videoId":"xIeyK7J1NOM","title":"6246 - نصيحة للنساء في حفظ اللسان عن الألفاظ الرديئة  - نور على الدرب","position":107},{"videoId":"XZVT80DlXoo","title":"6260 - مدى صحة القول باستمرار النعيم في القبر وحتى يوم القيامة  - نور على الدرب","position":108},{"videoId":"nTj-SXYect0","title":"6305 -  كيفية التصرف في الطعام المتبقي منذ أيام - نور على الدرب","position":109},{"videoId":"8MzjGd8hNAA","title":"6326 -  حكم عدم صلة الأرحام بسبب تباعد المسافات - نور على الدرب","position":110},{"videoId":"zJpIUAAn89s","title":"6350 -  حكم مقاطعة الأقارب إذا كانوا سيئين أخلاقياً - نور على الدرب","position":111},{"videoId":"gpY8EPPje1k","title":"6351 -  حكم رفع المرأة لصوتها في الصلاة من أجل تعليم الأبناء  - نور على الدرب","position":112},{"videoId":"ckjum_WcPJc","title":"6352 -  نصيحة للآباء في حث الأبناء على الصلاة والمحافظة عليها - نور على الدرب","position":113},{"videoId":"Vd1T7ZKRJcw","title":"6381 -  حكم مجالسة قرناء السوء  - نور على الدرب","position":114},{"videoId":"N177Uoqv7tE","title":"6461 -  حكم قول الأم لابنها يا حياتي .. يا عمري  - نور على الدرب","position":115},{"videoId":"9t3hvrSa9NA","title":"6473 -  كيفية تربية الأبناء تربية صحيحة - نور على الدرب","position":116},{"videoId":"nNGPmuXvy-w","title":"6512 -  كيفية سلام ومصافحة النساء الأجانب  - نور على الدرب","position":117},{"videoId":"ayYgPVgtpzk","title":"6540 -  حكم إحراق بعض أوراق المصحف خشية الامتهان  - نور على الدرب","position":118},{"videoId":"UOBPw-5MNPk","title":"6542 -  حكم تقبيل يدي الوالدين  - نور على الدرب","position":119},{"videoId":"TdkEeB-xQgQ","title":"6550 -  الأولاد والبنات إذا قاموا على والدهم الكبير لهم أجر إذا قاموا بتعليمه الصلاة - نور على الدرب","position":120},{"videoId":"2DX6ZZ41yWQ","title":"6643 -  حكم الاكتفاء بالاتصال الهاتفي في صلة الرحم - نور على الدرب","position":121},{"videoId":"umq-Bde8E3Q","title":"6664 -  كيفية التعامل مع من يقول بأنه غير مقتنع بالحجاب الشرعي  - نور على الدرب","position":122},{"videoId":"Usz5lLqCfWk","title":"6728 -  حكم إزالة ما ينبت بين الحاجبين من شعر  - نور على الدرب","position":123},{"videoId":"58YsEsFq6bQ","title":"6749 - حكم صلة الرحم عن طريق الهاتف - نور على الدرب","position":124},{"videoId":"0zXIoUDQtDY","title":"6762 -  حكم تأديب الأطفال دون سن العاشرة - نور على الدرب","position":125},{"videoId":"8GQUH3CyT98","title":"6769 -  فضل الصبر على المصائب - نور على الدرب","position":126},{"videoId":"U6xMWf8e_zg","title":"6771 -  أسباب السعادة  - نور على الدرب","position":127},{"videoId":"OyrCQ0jKmyk","title":"6778 -  بيان كنية أم المؤمنين عائشة رضي الله عنها - نور على الدرب","position":128},{"videoId":"BElnYAa1pKI","title":"6793 -  كيفية التخلص من الخواطر التي تأمر بالسوء وترك الواجبات - نور على الدرب","position":129},{"videoId":"6maP14vWW0s","title":"6829 -   حكم النوم بعد صلاة العصر  - نور على الدرب","position":130},{"videoId":"po_SVpvMhn0","title":"6839 -   حكم أكل الثوم والبصل في رمضان  - نور على الدرب","position":131},{"videoId":"slaFcPGDUnU","title":"6842 -   حكم الجهر بالبسملة في الطعام - نور على الدرب","position":132},{"videoId":"u2TlSITsxfw","title":"6857 -   حكم قتل الحشرات بالصاعق الكهربائي  - نور على الدرب","position":133},{"videoId":"4OMOQii2AOQ","title":"6903 - حكم الإثابة على الهدية - نور على الدرب","position":134},{"videoId":"mRrIf8yLDXY","title":"6917 - حكم الكلام أثناء الوضوء والأذان - نور على الدرب","position":135},{"videoId":"gtSGIKTXX0E","title":"6949 - حكم إصلاح الأسنان التي فيها اعوجاج  - نور على الدرب","position":136},{"videoId":"C45G8tzzis8","title":"6961 - كيفية البداءة بتقديم القهوة للرجال والنساء في الجلسات العائلية - نور على الدرب","position":137},{"videoId":"8DShQtxtz68","title":"6966 - كيفية تعامل الأم مع الأبناء الذين لا يصلون - نور على الدرب","position":138},{"videoId":"r-uFdaQHYjc","title":"6997 - حكم ذبح الماشية التي يخشى موتها - نور على الدرب","position":139},{"videoId":"zquFc-KRZ5I","title":"6996 - حكم اتخاذ الكلاب للحراسة - نور على الدرب","position":140},{"videoId":"ihbmxdUHsX0","title":"6974 - حكم قول (حسبنا الله ونعم الوكيل) من الزوجة لزوجها - نور على الدرب","position":141},{"videoId":"-Y7NMwwHBVw","title":"7052 - حكم صلة بنات العم والعمة وبنات الخال والخالة - نور على الدرب","position":142},{"videoId":"DgMsZsIfiZA","title":"7084 - حكم الوسوسة أثناء الصلاة - نور على الدرب","position":143},{"videoId":"k2YcVE6ndtg","title":"7104  -  كيفية التعامل مع الأخ إذا كان تاركاً للصلاة - نور على الدرب","position":144},{"videoId":"RwYHVAghae4","title":"7129 -  كيفية الصبر على المرض - نور على الدرب","position":145},{"videoId":"e50iIfLTNlw","title":"7151 -  موقف المسلم من اختلاف الفتوى - نور على الدرب","position":146},{"videoId":"k_DQqMV1fyU","title":"7162  -  واجب الآباء الذين يتساهلون في أمر أولادهم بالصلاة  - نور على الدرب","position":147},{"videoId":"oX83qLF0rIA","title":"7182 -  أجر زيارة المريض - نور على الدرب","position":148},{"videoId":"8WUvNcVBX8Q","title":"7196  -  حكم دخول البالغين من الأقارب على النساء - نور على الدرب","position":149},{"videoId":"yxvjlyHjwIA","title":"7219 -  حكم تقبيل أيدي كبار السن من القرابة - نور على الدرب","position":150},{"videoId":"yWuhaTo65bc","title":"7236 -  حكم ضرب الطفلة المريضة للتأديب - نور على الدرب","position":151},{"videoId":"l9Zbp8N4OR8","title":"7307 -  حكم الاعتقاد بأن وضع سرة المولود في الكتب يجعله يحب العلم - نور على الدرب","position":152},{"videoId":"TCbfuLqmM74","title":"7306 -  حكم تقبيل الصديق عند مجيئه من سفر أو غيره - نور على الدرب","position":153},{"videoId":"Kx3isCI4NMc","title":"7308 -  حكم احتجاب أم المولود في غرفة وحدها أربعين يوماً - نور على الدرب","position":154},{"videoId":"G7LmZrBrtjA","title":"7379 -  حكم اصطحاب الأطفال إلى المساجد - نور على الدرب","position":155},{"videoId":"bHfGtf8kBog","title":"7430 -  حكم اصطحاب الأطفال إلى المساجد - نور على الدرب","position":156},{"videoId":"jYqOIu4FD08","title":"7431 -  حكم من دهس جملاً بالسيارة خطأً - نور على الدرب","position":157},{"videoId":"WOlR6oz4faE","title":"7455 - أوقات استحباب السواك - نور على الدرب","position":158},{"videoId":"J4q6-8wt1Es","title":"7456 - حكم الصلاة في النعال - نور على الدرب","position":159},{"videoId":"MnBSPbzsnKI","title":"7537  - حكم الاختلاط ببعض الأسر بسبب رعاية شئونها - نور على الدرب","position":160},{"videoId":"t4K2F3gRaeo","title":"7540  - حكم رفع الصوت على الوالد - نور على الدرب","position":161},{"videoId":"gmXMrv3PJ-k","title":"7577 - حكم تعليق الآيات القرآنية والأحاديث النبوية على جدران المنازل -  نور على الدرب","position":162},{"videoId":"2wxhCbFLQuc","title":"7583 - حكم حمد الله من العاطس في الصلاة والتشميت له من غيره -  نور على الدرب","position":163},{"videoId":"w-bz-Tl5mFc","title":"7613 -  فضل صلة الرحم وزيارة الأقارب والإخوان  -  نور على الدرب","position":164},{"videoId":"n2Trhf9tigc","title":"7697 - حكم التسمي بأسماء فيها تعبيد لغير الله -  نور على الدرب","position":165},{"videoId":"sZXbK0KSYO0","title":"7698 - حكم وصف الإنسان بالسيد -  نور على الدرب","position":166},{"videoId":"xAN3fat7A3w","title":"7738 - حكم من لم يرد السلام على من سلم عليه -  نور على الدرب","position":167},{"videoId":"jwIRoNjrNMk","title":"7739 - حكم رد السلام سراً -  نور على الدرب","position":168},{"videoId":"ih-lQ9QQAnU","title":"7744 - حكم النكول في اليمين لعلة الإصلاح بين الناس  -  نور على الدرب","position":169},{"videoId":"Al1Wjo6sHUI","title":"7794 - حكم قراءة الفنجان والكف ورمي الودع وحكم إتيان أمثال هؤلاء -  نور على الدرب","position":170},{"videoId":"dGTiH69jNiU","title":"7810  - إجزاء سلام الفرد من الجماعة عن الباقين  -  نور على الدرب","position":171},{"videoId":"xTwc_bD0A7c","title":"7811  - بطلان القول بالنهي عن البناء أكثر من عشرة أذرع ارتفاعاً -  نور على الدرب","position":172},{"videoId":"6n4DxZeT0e8","title":"7816 - حكم إبعاد الأطفال من الصفوف الأولى في المسجد -  نور على الدرب","position":173},{"videoId":"xosleFElNZU","title":"7821 - حكم قول التلميذ لمعلمه أحسنت-  نور على الدرب","position":174},{"videoId":"8lyQT40pjZQ","title":"7827 - حكم جعل المصاحف خلف الصفوف -  نور على الدرب","position":175},{"videoId":"BDbSiUNU-Uc","title":"7857 - حكم إلقاء السلام على من في المسجد -  نور على الدرب","position":176},{"videoId":"_NM0TXLrsGU","title":"7913 - حكم إلقاء قصاصات الأظفار والشعر في القمامة  -  نور على الدرب","position":177},{"videoId":"nGpYd51no70","title":"8228 -  حكم مجالسة أصحاب المعاصي -  نور على الدرب","position":178},{"videoId":"g5sRRjZGmAg","title":"8288 -  حكم إجابة الوالدين أثناء الصلاة -  نور على الدرب","position":179},{"videoId":"sLFtKJkqOV8","title":"8401 -  مدى صحة عبارة (لا حياء في الدين) -  نور على الدرب","position":180},{"videoId":"sql754L6Hy4","title":"8428 -  الواجب على من كان لها أخ لا يصلي -  نور على الدرب","position":181},{"videoId":"5vzC1ZB22Us","title":"8451 - حكم الذبح من باب الضيافة والإكرام -  نور على الدرب","position":182},{"videoId":"BsZ2XPQQGcU","title":"8462 - حكم الاستهزاء بالمتحجبات -  نور على الدرب","position":183},{"videoId":"NXqe6AwjRdk","title":"8488 - حكم إخراج الأطفال من الصفوف في الصلاة -  نور على الدرب","position":184},{"videoId":"QT2qu9Lfjq4","title":"8513 - حكم أخذ الرجل من شعر الخدين والحاجب -  نور على الدرب","position":185},{"videoId":"M9ZNFLb9pxs","title":"8523 - حكم قبول المعلم هدايا الطلاب  -  نور على الدرب","position":186},{"videoId":"BPbuU3w1k10","title":"8544 - من سبق إلى مكان في الصف فهو أحق به  -  نور على الدرب","position":187},{"videoId":"RNn1MKVbCPk","title":"8550 - آداب دفن الميت  -  نور على الدرب","position":188},{"videoId":"njb6YcpOnq8","title":"8557 - حكم ترك الأظفار لأكثر من أربعين يوماً -  نور على الدرب","position":189},{"videoId":"j5Zqi3Pv06c","title":"8569 - حكم الضحك في الصلاة  -  نور على الدرب","position":190},{"videoId":"dCX6jUnn_hA","title":"8557 - حكم ترك الأظفار لأكثر من أربعين يوماً -  نور على الدرب","position":191},{"videoId":"CwNCT4euJPM","title":"8569 - حكم الضحك في الصلاة  -  نور على الدرب","position":192},{"videoId":"0PT0IUkerow","title":"8587 - حكم مرور الأطفال أمام المصلين  -  نور على الدرب","position":193},{"videoId":"Fhp0j6rqFek","title":"8624 - حكم الاشتغال بعمل ما أثناء سماع القرآن  -  نور على الدرب","position":194},{"videoId":"yP-3dvVuE4w","title":"8629  - حكم الكحل والطيب وغسل الرأس بالصابون  -  نور على الدرب","position":195},{"videoId":"cmQE4BTG6CY","title":"8661 - حكم تحدث الخاطب إلى المخطوبة -  نور على الدرب","position":196},{"videoId":"4NFQZ4XxgEQ","title":"8719 - حكم مجالسة شارب الخمر -  نور على الدرب","position":197},{"videoId":"LWagxNvEMEc","title":"8723 - حكم السلام على الأجنبية -  نور على الدرب","position":198},{"videoId":"Ic00UfJFBqE","title":"8724 - حكم سب البهائم ولعنها -  نور على الدرب","position":199},{"videoId":"VY1-KkLHDCY","title":"8759 - حكم استخدام السواك أثناء خطبة الجمعة  -  نور على الدرب","position":200},{"videoId":"wdYWY7hN6-w","title":"8951 - حكم عيادة المرأة للمريض الأجنبي -  نور على الدرب","position":201},{"videoId":"mPilGr1WYgo","title":"9017 - الواجب على الأم تجاه الابن التارك للصلاة -  نور على الدرب","position":202},{"videoId":"WFocjYfGBuM","title":"9035 -  حكم التعوذ بعد التثاؤب -  نور على الدرب","position":203},{"videoId":"HaoHhA0bonc","title":"9075 -  حكم الكلام على الناس في غيبتهم -  نور على الدرب","position":204},{"videoId":"qs61u8lcxjY","title":"9110 -  حكم التسخط الناتج عن فقدان الشعور بسبب المصيبة -  نور على الدرب","position":205},{"videoId":"h9in0RHw_p0","title":"9140 -   حكم التسوق في مكة بعد طواف الوداع -  نور على الدرب","position":206},{"videoId":"tETUtWh3WTg","title":"9142 -   حكم تطييب ملابس الإحرام  -  نور على الدرب","position":207},{"videoId":"ZAXMSjcgsl4","title":"9141 - بيان الخطأ في اعتقاد لزوم لمس كل الأشياء التي سيستخدمها الحاج أو المعتمر عند عقد نية الإحرام","position":208},{"videoId":"rWewPiDAgCk","title":"9201 - وسائل التربية الصحيحة للأبناء في المحافظة على الصلوات والالتزام بأمور الدين -  نور على الدرب","position":209},{"videoId":"Ag2774cFoV4","title":"9202 - الحرص على التربية الإسلامية منذ الصغر -  نور على الدرب","position":210},{"videoId":"73a_aAZQoUY","title":"9232  - حكم زيادة (وبركاته) في السلام -  نور على الدرب","position":211},{"videoId":"bNHcXU_mG1E","title":"9252 - حكم إهداء الطالب للمدرس  -  نور على الدرب","position":212},{"videoId":"S6Q5p8ngYcs","title":"9394 - حكم زيارة المرأة لجيرانها دون إذن زوجها  -  نور على الدرب","position":213},{"videoId":"JK3Vl7qisQ4","title":"9438 - حكم من دعاه جاره لزيارته فاعتذر بالانشغال لعدم رغبته في زيارته  -  نور على الدرب","position":214},{"videoId":"yq21Z82jbzI","title":"9568 -  آداب الدعاء -  نور على الدرب","position":215},{"videoId":"87tV7BUYAMk","title":"9570 -  حكم المصافحة عقب الانصراف من الصلاة  -  نور على الدرب","position":216},{"videoId":"hSgLbHzDWw4","title":"9571 -  حكم مصافحة المرأة الكبيرة من غير المحارم  -  نور على الدرب","position":217},{"videoId":"xbR7gyXHnZE","title":"9636 -  حكم إهمال الإمام عمله وإنابة غيره عنه  -  نور على الدرب","position":218},{"videoId":"2Sb4XgH3I4U","title":"9679 -  حكم إخبار الرجل زوجته بأمور فيها غيبة لشخص آخر -  نور على الدرب","position":219},{"videoId":"-r_ChylEQQw","title":"9684 -  حكم الخلوة بالأجنبية -  نور على الدرب","position":220},{"videoId":"vQXx-NX42RA","title":"9776 - بعض أحكام وآداب الإقامة بمكة والمدينة -  نور على الدرب","position":221},{"videoId":"4IS5xB9dg0w","title":"9786 - حكم تقبيل يدي أهل الفضل والجاه والصلاح والوالدين  -  نور على الدرب","position":222},{"videoId":"TK-c8_InN9o","title":"9863 -حكم انقطاع المرأة عن زيارة أقاربها وجيرانها بسبب ما في مجالسهم من النميمة أو غيرها من المنكرات","position":223},{"videoId":"pgpdPYt9RG4","title":"9889 -  حكم مصافحة الفتاة التي لم يتجاوز عمرها الحادية عشرة -  نور على الدرب","position":224},{"videoId":"6od76e0ceNI","title":"10037 - حكم زيارة الأقارب البعيدين -  نور على الدرب","position":225},{"videoId":"psX0YNXqyu8","title":"10038 - محرمية خال الأم وعمها -  نور على الدرب","position":226},{"videoId":"ymRzeuVUMDI","title":"10060 -   الحث على التزاور بين الإخوان -  نور على الدرب","position":227},{"videoId":"PJjH9QNr2zE","title":"10070 - كيفية تعامل الأب مع ابنه التارك للصلاة -  نور على الدرب","position":228},{"videoId":"tP_ezclwjxQ","title":"10111 - بطلان القول بتحريم السواك على النساء -  نور على الدرب","position":229},{"videoId":"TsDOYuwAqqs","title":"10131 - حكم البكاء أثناء الصلاة -  نور على الدرب","position":230},{"videoId":"j7VV78eyWYs","title":"10170 - حكم من سمع الأغاني من غير قصد  -  نور على الدرب","position":231},{"videoId":"xxDWbyPA4Uw","title":"10198 -  حكم التقبيل والانحناء عند السلام  -  نور على الدرب","position":232},{"videoId":"AvPG5lJCpMM","title":"10217 -  حكم مصاحبة تارك الصلاة -  نور على الدرب","position":233},{"videoId":"2WdjBHijmKw","title":"10291  - حكم مصافحة المرأة للرجل الأجنبي المسن  -  نور على الدرب","position":234},{"videoId":"kcitkPwTrPk","title":"10299 - حكم تفضيل شخص على شخص في أمر ما وإمكانية دخول ذلك في الغيبة المحرمة -  نور على الدرب","position":235},{"videoId":"WjXHyS198fU","title":"10306 - حكم الأكل مع من لا يصلي  -  نور على الدرب","position":236},{"videoId":"xTbCP80SX7g","title":"10324 - حكم تقبيل الأيدي بعد الصلاة  -  نور على الدرب","position":237},{"videoId":"4uTbEdfXt0w","title":"10495 -  حكم السكن مع القريب الذي لا يصلي أحياناً  -  نور على الدرب","position":238},{"videoId":"9L1uRLst0KI","title":"10527 -  الواجب على من كان بينهما عداوة وشحناء -  نور على الدرب","position":239},{"videoId":"J_814VWhlwk","title":"10549 -  حكم إجابة الوالدين وفي حضرتهما منكر كالتلفاز مثلاً  -  نور على الدرب","position":240},{"videoId":"5hC4UG4Uw7Q","title":"10550  -  هل هناك  حد معين لطاعة الوالدين؟ -  نور على الدرب","position":241},{"videoId":"n4f1HJm3ixo","title":"10550  -  هل هناك  حد معين لطاعة الوالدين؟ -  نور على الدرب","position":242},{"videoId":"zLF2_WpT7zw","title":"10555 - حكم إلقاء السلام على من لا يصلي -  نور على الدرب","position":243},{"videoId":"HD_xhUXimIY","title":"10656 - حكم السكن مع الأقارب مع وجود اختلاط  -  نور على الدرب","position":244},{"videoId":"ndRwGjAKxaw","title":"10699 - مشروعية تأديب اليتيم إذا أساء من قبل القائم على رعايته -  نور على الدرب","position":245},{"videoId":"qHBzTAzowU8","title":"10707  - حكم قول القائل (صدفة) أو من (حسن الحظ) -  نور على الدرب","position":246},{"videoId":"SXneLN1jhjE","title":"10782 -  الجمع بين الأحاديث التي تنهى عن الأكل والشرب قائماً وبين الأحاديث المبيحة لذلك","position":247},{"videoId":"jpemcuCxi7k","title":"10788 -  الأشخاص الذين يجوز للمرأة مصافحتهم -  نور على الدرب","position":248},{"videoId":"dtzscBsObIA","title":"10789 -  مشروعية نصح المرأة لأقاربها من الرجال وقراءة القرآن عليهم ما لم تخش فتنة -  نور على الدرب","position":249},{"videoId":"3JBT_2slNrs","title":"10856  - حكم مناداة الشخص بلفظ (السيد) -  نور على الدرب","position":250},{"videoId":"VLA_Tk3_6PI","title":"10913 - حكم ترك الأغنام بغير راع وأكل الذئاب منها والسباع -  نور على الدرب","position":251},{"videoId":"SAfpQR8leZk","title":"10942 - حكم المسامحة للظالم عند عدم المقدرة على الاقتصاص منهم -  نور على الدرب","position":252},{"videoId":"-MhH0xGeZ_Y","title":"10949 - ما يشرع للجماعة إذا سلم عليهم شخص واحد -  نور على الدرب","position":253},{"videoId":"rqA6v_Wxo68","title":"10950 - مشروعية أمر الأطفال بالصلاة إذا بلغوا سبعاً -  نور على الدرب","position":254},{"videoId":"s15YmwLWTS0","title":"10981- حكم صلة المرأة أقارب زوجها إذا كانوا لا يرغبون فيها -  نور على الدرب","position":255},{"videoId":"9qeqOiFo0ck","title":"10971 - المدة المسموح بها في الشرع لمفارقة الزوجة لأجل العمل -  نور على الدرب","position":256},{"videoId":"iDLraxvwcV4","title":"11023 - حكم إلقاء السلام عند دخول المنزل إذا لم يكن فيه أحد  -  نور على الدرب","position":257},{"videoId":"elic_MAuAoQ","title":"11026 - حكم إلقاء السلام على غير المسلمين -  نور على الدرب","position":258},{"videoId":"mWWluYzjszU","title":"11023 - حكم إلقاء السلام عند دخول المنزل إذا لم يكن فيه أحد  -  نور على الدرب","position":259},{"videoId":"6Lr9g_jraJo","title":"11026 - حكم إلقاء السلام على غير المسلمين -  نور على الدرب","position":260},{"videoId":"CZ9t0Zxj_Jc","title":"11151 - حكم تقصير اللحية -  نور على الدرب","position":261},{"videoId":"gM6v1PCzOu8","title":"11177 - حدود العلاقة بين المرأة وأهل بيت تربت عندهم وليسوا محارم لها -  نور على الدرب","position":262},{"videoId":"pIb64bwz3aQ","title":"11178 - حكم تعليق الآيات والأحاديث للفائدة والتذكير -  نور على الدرب","position":263},{"videoId":"QIW7ToJSy0c","title":"11195 - حكم زيادة (وبركاته) عند السلام من الصلاة -  نور على الدرب","position":264},{"videoId":"4D7STXcJDcU","title":"11196 - حكم قول إني متوكل على الله ثم عليك أن تفعل لي كذا  -  نور على الدرب","position":265},{"videoId":"2TdqglAvcsk","title":"11251 - حكم تعليق الصور -  نور على الدرب","position":266},{"videoId":"iE5O7CKZc88","title":"11262 - حكم مقاطعة من لا يأمر بالمعروف ولا ينهى عن المنكر -  نور على الدرب","position":267},{"videoId":"-zoY5vD1yt0","title":"11291 - حكم السلام على الكافر  -  نور على الدرب","position":268},{"videoId":"IAyQ2E4oMcQ","title":"11349 - حكم الإسراف والتبذير في الأكل والشرب -  نور على الدرب","position":269},{"videoId":"i3wOLP3T6fc","title":"11369 - حكم قول المسلم لأخيه المسلم إذا نصحه لك دينك ولي ديني -  نور على الدرب","position":270},{"videoId":"jkY5qckQaTw","title":"11371 - حكم ترطيب الأصبع باللعاب عند تقليب صفحات المصحف -  نور على الدرب","position":271},{"videoId":"2sBGL8FuqDc","title":"11458 - حكم تباهي بعض الرجال بالأسرار الزوجية أمام الآخرين  -  نور على الدرب","position":272},{"videoId":"DaDSGC7bvco","title":"11502 - حكم اتصال المرأة برجل لتستفتي في أمر دينها -  نور على الدرب","position":273},{"videoId":"4TpekhlM5_s","title":"11566 - كيفية التعامل مع الوالدين إذا اختلفا وتشاجرا -  نور على الدرب","position":274},{"videoId":"AEhC4yOG2Ps","title":"11571 - حكم تقبيل الأبناء أيادي آبائهم أو أمهاتهم  -  نور على الدرب","position":275},{"videoId":"qnTFh8V7-os","title":"11582 - حكم الوساوس التي تحمل على سوء الظن بالناس وكيفية علاجها -  نور على الدرب","position":276},{"videoId":"2umPydPMKtw","title":"11596 - حكم الجلوس مع قريب تارك للصلاة وشارب للخمر -  نور على الدرب","position":277},{"videoId":"QYVOdzFzrC8","title":"11619 - حكم قبول المدرس هدية الطالب -  نور على الدرب","position":278},{"videoId":"7NxDQ7muums","title":"11635 - حكم تشبيك اليدين في المسجد  -  نور على الدرب","position":279},{"videoId":"eqpoLuVYW4M","title":"11644 - حكم السلام على المرأة ورد السلام عليها  -  نور على الدرب","position":280},{"videoId":"PDUE2tlp_EI","title":"11651 - حكم السلام والكشف على أم الصديق -  نور على الدرب","position":281},{"videoId":"P_JD36wl5FQ","title":"11654 - حكم جلوس الإخوة مع نسائهم في مجلس واحد بحشمة وحجاب -  نور على الدرب","position":282},{"videoId":"G8Y3zZsJIOU","title":"11701 - حكم صيام الرجال والنساء إذا اختلطوا في نهار رمضان للعب ونحوه -  نور على الدرب","position":283},{"videoId":"O86MQZiZFko","title":"11706 - حكم مصافحة البنت التي لم تبلغ -  نور على الدرب","position":284},{"videoId":"gpOBIK4zITA","title":"11707 - معنى قوله تعالى (ويسألونك عن ذي القرنين قل سأتلو عليكم منه ذكراً...) -  نور على الدرب","position":285},{"videoId":"9A28i-mZ9Bo","title":"11712 - حكم مصافحة المرأة للأجانب ومخالطتهم، وحكم مجالسة من تفعل ذلك -  نور على الدرب","position":286},{"videoId":"Mb6DqawUs_I","title":"11714 - حكم دعاء الوالدة على أولادها وضربهم -  نور على الدرب","position":287},{"videoId":"RSFtu2N0is8","title":"11731 - حكم الجلوس مع من يغتاب وينم من دون نصحه -  نور على الدرب","position":288},{"videoId":"dqinqiBR8bI","title":"11773 - حكم التقاطع بين الجيران لأكثر من ثلاثة أيام -  نور على الدرب","position":289},{"videoId":"tgaDWntJNbs","title":"11776 - حكم الجلوس في المجالس التي يكثر فيها المزاح -  نور على الدرب","position":290},{"videoId":"MWXcTVcxLK4","title":"11777 - حكم مصافحة النساء -  نور على الدرب","position":291},{"videoId":"I2FwOtu4Hkg","title":"11778 - حكم مصافحة الداخل كل من في المجلس أو بعضهم -  نور على الدرب","position":292},{"videoId":"snJjM4NtTHE","title":"11779 - هيئة المصافحة -  نور على الدرب","position":293},{"videoId":"4aQZOoABvTc","title":"11834 - حكم رد السلام على من سلم في آخر الصلاة -  نور على الدرب","position":294},{"videoId":"jIibQB9wR7E","title":"11846 - حكم ترك زيارة الجيران إذا كانوا أهل شر -  نور على الدرب","position":295},{"videoId":"5A_asm2wcx8","title":"11842 - حكم منفعة القريبة غير المحرم إذا لم يكن لديها أحد وكيفية ذلك -  نور على الدرب","position":296},{"videoId":"FqHGbWigD6k","title":"11841 - حكم تعزية من يقيم الولائم والمآتم -  نور على الدرب","position":297},{"videoId":"m_U9QQ2ynHc","title":"11840 - حكم التعامل مع تارك الصلاة -  نور على الدرب","position":298}]