[{"videoId":"3OtrZ-ZSBe8","title":"01   ما حكم تولي المرأة القضاء؟ للإمام ابن باز","position":0},{"videoId":"ysRhUHL5Rzs","title":"02   هل السلام الوطني للدول جائز شرعا؟ للإمام ابن باز","position":1},{"videoId":"twYem7jkjNI","title":"03   هل أهل نجران من الشيعة؟ وكيف يكون التعامل معهم؟ للإمام ابن باز","position":2},{"videoId":"JEXzhrdR-84","title":"04   ما الواجب على من لديه عمال كفار ويجهرون بكفرهم؟ للإمام ابن باز","position":3},{"videoId":"2V8lDgS9LKg","title":"05   ما العمل تجاه من حكم بغير ما أنزل الله؟ للإمام ابن باز","position":4},{"videoId":"YO9VidOp024","title":"06   ما حكم ترك تحكيم شرع الله؟ للإمام ابن باز","position":5},{"videoId":"kjk5691wZlo","title":"07   ما حكم بذل الحاكم المسلم المال لدولة غير مسلمة؟ للإمام ابن باز","position":6},{"videoId":"Cpw_ur4PSKA","title":"08   ما عقوبة التقاعس عن الشهادة؟ للإمام ابن باز","position":7},{"videoId":"CEKxbAJVwOk","title":"09   ما العمل مع أسماء الكفار المخالفة لشرعنا في دائرة السفارات والجوازات؟ للإمام ابن باز","position":8},{"videoId":"Pk2eipEI4G4","title":"10   هل حديث أخرجوا المشركين من جزيرة العرب عام في كل المشركين؟ للإمام ابن باز","position":9},{"videoId":"iTtbFwkuzCo","title":"11   ما حكم إقامة المبتعث للدراسة في بيوت الكافرين؟ للإمام ابن باز","position":10},{"videoId":"yCuHSv8ly8g","title":"12   هل يحاسب ولي الأمر على سفر المسلمين إلى بلاد الكفر للمعصية؟ للإمام ابن باز","position":11},{"videoId":"Eg_E9ArtfPA","title":"13   ما حكم الرد بالسام على الكافر إذا بدأنا بالسلام؟ للإمام ابن باز","position":12},{"videoId":"wK8DgcHjzYc","title":"14   هل من بديل لإحضار خادمة بين أولادي المراهقين؟ للإمام ابن باز","position":13},{"videoId":"YS3Qt-0QUo4","title":"15   هل الخدم اليوم لهم نفس أحكام الخدم في عهد النبي؟ للإمام ابن باز","position":14},{"videoId":"TgraM-bSpws","title":"16   ما حكم التجسس على الساحر هاتك العرض وقتله؟ للإمام ابن باز","position":15},{"videoId":"t2a9_-iOIV0","title":"17   هل يجوز المسامحة في الحقوق قبل أن تبلغ السلطان؟ للإمام ابن باز","position":16},{"videoId":"u1oBn-bYpmU","title":"18   ما ردكم على ما وجهته إذاعة لندن لكم من هجوم؟ للإمام ابن باز","position":17},{"videoId":"iduqRSITup8","title":"19   ما حكم العمل مع من لا يلتزمون بشعائر وأخلاق الإسلام؟ وهل يفضل اعتزالهم؟ للإمام ابن باز","position":18},{"videoId":"fBa6_vKFCjg","title":"20   ما حكم دفع المال لدفع ضرر أو للحصول على حق؟ وهل هذا من الرشوة المحرمة؟ للإمام ابن باز","position":19},{"videoId":"8B_IsFiRkRg","title":"21   ما حكم التشبه بلباس الكفار في بلادهم تجنبا للإحراج والفتنة ؟ للإمام ابن باز","position":20},{"videoId":"QNvqPRSjYys","title":"22   ما حكم استقدام مربيات غير مسلمات لتربية الأولاد؟ للإمام ابن باز","position":21},{"videoId":"5-ldPOf3jNE","title":"23   هل يصح إعطاء النصارى إجازة في أعيادهم؟ للإمام ابن باز","position":22},{"videoId":"NOeevUEi3_4","title":"24   ما الطريق الصحيح لإقامة شرع الله في الأرض؟ للإمام ابن باز","position":23},{"videoId":"0oievEqzxQU","title":"25   ما كيفية اعتبار الدولة دولة إسلامية؟ للإمام ابن باز","position":24},{"videoId":"Snml-3b2dDo","title":"26   ما مدى صحة الحكم بأحكام تخالف الشريعة الإسلامية؟ للإمام ابن باز","position":25},{"videoId":"Dt1IGrL3KYc","title":"27   ما رأيكم في تطبيق الأحكام في البلاد الإسلامية على الضعفاء فقط؟ للإمام ابن باز","position":26},{"videoId":"qDs24m_0S8A","title":"28   ما العمل فيمن يعملون في الدوائر الحكومية ويحكمون بغير ما أنزل الله؟ للإمام ابن باز","position":27},{"videoId":"1KyyD4hEt20","title":"29   هل يجوز التعاون مع الدول الإسلامية التي تحكم بقوانين وضعية؟ للإمام ابن باز","position":28},{"videoId":"XBeS1nQPsQ4","title":"30   هل يصح تحالف المسلم مع أصحاب الفكر الشيوعي والقومي وغيرهم؟ للإمام ابن باز","position":29},{"videoId":"RW_zUi7cvMY","title":"31   ما عقوبة التحاكم إلى الطواغيت من أجل تحقيق مصالح دنيوية؟ للإمام ابن باز","position":30},{"videoId":"CUzMWm6Di_0","title":"32   هل تجب مساندة وتأييد من يريد الحكم بشرع الله؟ للإمام ابن باز","position":31},{"videoId":"dn6Lynm09AM","title":"33   ما حكم تقنين الشريعة الإسلامية؟ للإمام ابن باز","position":32},{"videoId":"L7lXLn4VmsY","title":"34   ما حكم العمل في المباحث مع كون العمل يتطلب التجسس على المسلمين؟ للإمام ابن باز","position":33},{"videoId":"7TY3DhF9xxc","title":"35   هل يجوز الخروج على الحاكم الذي يحكم بغير ما أنزل الله؟ للإمام ابن باز","position":34},{"videoId":"QF6nHnv_YTQ","title":"36   ما الرد على من يقولون بلادنا التي تطبق الشريعة، والبلاد كثرت فيها المنكرات والمعاصي؟","position":35},{"videoId":"D3yOIf4ReXo","title":"37   ما واجبنا تجاه المسلمين المضطهدين في بلاد العالم؟ للإمام ابن باز","position":36},{"videoId":"k9oNyf65VAo","title":"38   ما حكم قتال جيوش المسلمين بعضها البعض؟ للإمام ابن باز","position":37},{"videoId":"VwEeb9-08F8","title":"39   هل يجوز تتبع العلماء للحصول على الفتوى التي توافق الهوى؟  للإمام ابن باز","position":38},{"videoId":"hFBY2WnUEWY","title":"40   هل تتساوى الخادمة أو العاملة مع الأمة؟ للإمام ابن باز","position":39},{"videoId":"l0vOy6K-XZE","title":"41   ما حكم مشاركة المرأة في مختلف جوانب الحياة السياسية والاقتصادية؟ للإمام ابن باز","position":40},{"videoId":"2iWKgoDl0A8","title":"42   ما حكم إهداء غير المسلم نسخا من المصاحف المترجمة للتعرف على الإسلام؟ للإمام ابن باز","position":41},{"videoId":"JEmHwnKyAw0","title":"43   ما حكم طاعة ولي الأمر بالمشاركة في حروب أهلية بين مسلمين؟ للإمام ابن باز","position":42},{"videoId":"EU_iTKafPTc","title":"44   ما هي الخطوات التي يجب أن يتبعها حكام المسلمين لتحسين حال الأقليات الإسلامية ماديا ومعنويا؟","position":43},{"videoId":"Jlro7bH84S8","title":"45   ما حكم تقليد الغرب في أزيائهم؟ للإمام ابن باز","position":44},{"videoId":"UPvORRetUbI","title":"46   ما حكم الإقدام على القضاء والحكم مع القدرة عليه؟ للإمام ابن باز","position":45},{"videoId":"NltGnnICvDg","title":"47   ما حكم أطفال غير المسلمين؟ للإمام ابن باز","position":46},{"videoId":"yFGP34nDDfE","title":"48   ماذا عن التعصب الطبقي فيما يسمى حضري وقبلي؟ للإمام ابن باز","position":47},{"videoId":"6iYBMVqtX1Y","title":"49   كيف تكون المعاملة مع الشيعة؟ للإمام ابن باز","position":48},{"videoId":"VKsD8UKfzTo","title":"50   هل يوجد أصحاب ديانات أخرى غير الإسلام يعيشون في شبه الجزيرة الآن؟ للإمام ابن باز","position":49},{"videoId":"F4-Xmb-Q0mo","title":"51   كيف يكون الجمع بين حديث مضايقة الكفار وآية الإحسان إليهم؟ للإمام ابن باز","position":50},{"videoId":"DshnJ1XFn-g","title":"52   واجب المسلمين تجاه الكافرين العاملين في بلادهم للإمام ابن باز","position":51},{"videoId":"frbCLFavIiA","title":"53   كيف يكون تطبيق الشريعة الإسلامية على الكفار في بلاد المسلمين؟ للإمام ابن باز","position":52},{"videoId":"Dqj7KV2kaQo","title":"54   فهل يجوز قتل الحاكم الذي عطل الحدود وفتح الخمارات وسجن المسلمين وحد من بناء المساجد؟","position":53},{"videoId":"991jVUMpp2g","title":"55   توجيهكم لظاهرة وضع الرجل الأجنبي  السائق  في البيت؟  للإمام ابن باز","position":54},{"videoId":"x26vnPfbFn8","title":"56     ما حكم طفل الأنابيب؟ للإمام ابن باز","position":55},{"videoId":"ypITestJUuY","title":"57   ما حكم ترك تحكيم شريعة الله؟ للإمام ابن باز","position":56},{"videoId":"wGhpvDX1j74","title":"58   حكم تطبيق بعض حدود الشريعة دون بعض؟ للإمام ابن باز","position":57},{"videoId":"givxrFFaJmc","title":"59   ما التصرف الصحيح شرعا في مجابهة الإعراض التي تقوم به دولة لا تطبق شرع الله؟ للإمام ابن باز","position":58},{"videoId":"GhLFlYYiARU","title":"60   من حكم بغير ما أنزل الله وهو يعتقد أن حكم الله هو الأفضل؟  للإمام ابن باز","position":59},{"videoId":"BlGGu3kazwo","title":"61   ما مشروعية الصلح مع العدو بشكل دائم؟ للإمام ابن باز","position":60},{"videoId":"OeBcbMbkRAE","title":"62   ما هي طريقة التعامل مع الشيعة؟  للإمام ابن باز","position":61},{"videoId":"LN8-NdqOPCI","title":"63   في البلاد الكافرة هل نبدأ بنصح  الحاكم ولو باليد، أم بتربية الفرد المسلم؟ للإمام ابن باز","position":62},{"videoId":"wB5dWapKXZI","title":"64   هل يشرع ما يسمى بتقنين الشريعة؟ للإمام ابن باز","position":63},{"videoId":"WSZKYtVep84","title":"65   ما حكم المضطر للتحاكم إلى القوانين الوضعية للإمام ابن باز","position":64},{"videoId":"0pRJqCXomrA","title":"66   ما حكم التحاكم للقانون الوضعي لأخذ الحق للإمام ابن باز","position":65},{"videoId":"PRrvd5TqZdg","title":"67   هل يأثم القاضي بالحكم بالقانون الوضعي؟ للإمام ابن باز","position":66},{"videoId":"3gwgEouIf8M","title":"68   ما واجب الرعية تجاه الحاكم الذي لا يطبق شرع الله للإمام ابن باز","position":67},{"videoId":"oXqTsZmXdrw","title":"69   هل تكون الدولة مسلمة بتطبيق جزء من شرع الله دون الجزء الآخر؟ للإمام ابن باز","position":68},{"videoId":"Azgnsv9zrA8","title":"70   ما حكم موالاة الدول العربية والإسلامية لأمريكا وأوروبا؟ للإمام ابن باز","position":69},{"videoId":"NBu9Ia7bt6U","title":"71   ما الطريق لتحقيق الأمن في الدول التي يحكمها الظالمون بغير ما أنزل الله؟ للإمام ابن باز","position":70},{"videoId":"PWuncDZrxAk","title":"72   هل يجوز التعامل مع الرافضة؟ للإمام ابن باز","position":71},{"videoId":"2cKiqO4pYMg","title":"73   هل يجوز القبض على المبشرين في حي الفيصلية بالرياض؟ للإمام ابن باز","position":72},{"videoId":"8sDnbba4Of0","title":"74   ما نصيحتكم بخصوص الرجال الذين ترسلهم الدولة في بعض الأماكن لمراقبة الدعاة والخطباء والشارع...","position":73},{"videoId":"wdpk7UQ5yPQ","title":"75   تكلمتم عن جواز التصالح مع اليهود في أرض فلسطين وهم أهل النفاق، نرجو توضيح هذه النقطة ؟","position":74},{"videoId":"D4dulaiJB_g","title":"76   ما حكم الإسلام في بعض المنافقين الذين يكتبون في الصحف ويؤججون نار الفتنه؟ وما هي نصيحتكم لهم؟","position":75},{"videoId":"U3fJzXu8uQo","title":"77   ما رأيكم فيمن ينكر فضح بعض العلمانيين مستدلين بأن النبي كان لا يصرح بأسماء المنافقين بل يقول...","position":76},{"videoId":"uFbq9xWIers","title":"78   ما حكم الجاسوس إذا قبض عليه قال ما فعلت ذلك إلا لخوف من أعداء الله؟ للإمام ابن باز","position":77},{"videoId":"oOKpSIuYFXs","title":"79   ما حكم من يعمل بالشريعة ظاهرا ويخالفها باطنا وإذا كان أميرا هل يجوز الخروج عليه؟ للإمام ابن باز","position":78},{"videoId":"sZGGwrCS4B4","title":"80   هل للحاكم أن يتصرف حسب ما يرى سياسيا وإن كان مخالفا للشريعة؟ للإمام ابن باز","position":79},{"videoId":"JuWkReLqntM","title":"81   لماذا لا نرد على أعداء الله من اليهود والزنادقة حول بث الشبهات حول الشريعة الإسلامية؟","position":80},{"videoId":"ps5AvFCukUY","title":"82   ماذا أصنع إذا أرسلت لحيتي ولكن حين سفري لبلادي أسجن بسببها؟ للإمام ابن باز","position":81},{"videoId":"vCogp7Gv9DY","title":"83   هل الحاكم الذي يحكم بغير شرع الله ويحكم الناس بالقوانين له سمع وطاعة وتصح ولايته لأمور المسلمين","position":82},{"videoId":"SQp81e4EqGo","title":"84   ما حكم الشرع فيمن يربي الشباب على بغض ولاة الأمر والوقوع في أعراض العلماء وغيبتهم؟","position":83},{"videoId":"i16IBUoQJMA","title":"85   ما ضوابط التحاكم للقوانين الوضعية للمضطر؟ للإمام ابن باز","position":84},{"videoId":"xsPb37cfZnw","title":"86   حكم الاعتداء على السائح المستأمن الرد على من يحل دم السائح في بلاد المسلمين، ونصيحة له","position":85},{"videoId":"P42n1SmHMKU","title":"87   هل الخروج على الحاكم يكون بالسيف أم باللسان؟ للإمام ابن باز","position":86},{"videoId":"4FerDkoKB1k","title":"88   ما حكم الحقوق الشخصية بين الناس؟هل يحرم ما يسمى بالحق بين المتخاصمين؟ للإمام ابن باز","position":87},{"videoId":"VHXP2OpjBXg","title":"89   نصيحتكم بخصوص من يقول أن العداوة بيننا وبين اليهود من أجل الأرض لا العقيدة؟ للإمام ابن باز","position":88},{"videoId":"6qHV1uG4Az8","title":"90   هل التحاكم إلى أعراف البادية وإلى السلوم المتوارثة؟ للإمام ابن باز","position":89},{"videoId":"bTaLRzmo__Y","title":"91   ما ضابط التعامل مع الكفار لتأليف قلوبهم للإسلام؟ للإمام ابن باز","position":90},{"videoId":"b7en5LGZohE","title":"92   هل يجوز التعاون مع النصارى في أي مجال؟ للإمام ابن باز","position":91},{"videoId":"XWoO_8NLODw","title":"93   هل يجوز التجنس بجنسية دولة كافرة؟ للإمام ابن باز","position":92},{"videoId":"5IrK8sDdT-0","title":"94   هل يصح شرعا ما يسمى بحوارات تقارب الأديان؟ للإمام ابن باز","position":93},{"videoId":"Jl3w6gekXTE","title":"95   هل يكره غير المسلم على الدخول في الإسلام؟ للإمام ابن باز","position":94},{"videoId":"4GTT7Lt5Ep8","title":"96   هل يجوز إلغاء تطبيق الشريعة بجنوب السودان بأي قوانين يرتضونها؟ للإمام ابن باز","position":95},{"videoId":"W8GiYqJNQsM","title":"97   ما حكم طاعة الحاكم الذي لا يطبق حكم الله ويطبق القانون الوضعي؟ للإمام ابن باز","position":96},{"videoId":"nMlVtofKGTE","title":"98   ما رأيكم في الحرب القائمة بين العراق وإيران؟ للإمام ابن باز","position":97}]