[{"videoId":"4J6abye1gFM","title":"شرح نونية ابن القيم(1) -المقدمة(1) -الثلاثاء 18-1-1441هـ","position":0},{"videoId":"bKlkDwtMT9I","title":"شرح نونية ابن القيم(2) -المقدمة(2) -الثلاثاء 03-2-1441هـ","position":1},{"videoId":"1CCcxouxUUQ","title":"شرح نونية ابن القيم(3) -المقدمة(3) -الثلاثاء 09-2-1441هـ","position":2},{"videoId":"sj3-eipBADI","title":"شرح نونية ابن القيم(4) -المقدمة(4) -الثلاثاء 16-2-1441هـ","position":3},{"videoId":"xsIROczv1m0","title":"شرح نونية ابن القيم(5) -المقدمة(5) -الثلاثاء 23-2-1441هـ","position":4},{"videoId":"6oqofNvhiiU","title":"شرح نونية ابن القيم(6) -المقدمة(6) -الثلاثاء 1-3-1441هـ","position":5},{"videoId":"aKDAKvihL9I","title":"شرح نونية ابن القيم(7) -المقدمة(7) -الثلاثاء 8-3-1441هـ","position":6},{"videoId":"UnzHKcBUpUM","title":"شرح نونية ابن القيم(8) -المقدمة(8) -الثلاثاء 15-3-1441هـ","position":7},{"videoId":"39DRVXlegX0","title":"شرح نونية ابن القيم(9) -المقدمة(9) -الثلاثاء 29-3-1441هـ","position":8},{"videoId":"6rIPzc_PNwg","title":"شرح نونية ابن القيم(10) -المقدمة(10) -الثلاثاء 6-3-1441هـ","position":9},{"videoId":"TnGvHopStlI","title":"شرح نونية ابن القيم(11) -المقدمة(11) -الثلاثاء 3-6-1441هـ","position":10},{"videoId":"UG8r0RksuPk","title":"شرح نونية ابن القيم(12) -المقدمة(12) -الثلاثاء 10-6-1441هـ","position":11},{"videoId":"4Yk8DgNosy4","title":"شرح نونية ابن القيم(13) -المقدمة(13) -الثلاثاء 17-6-1441هـ","position":12},{"videoId":"B4mO9KI_Iqw","title":"شرح نونية ابن القيم(14) -المقدمة(14) -الثلاثاء 24-6-1441هـ","position":13},{"videoId":"h0kKPcoSHZM","title":"شرح نونية ابن القيم(15) -المقدمة(15) -الثلاثاء 1-7-1441هـ","position":14},{"videoId":"PM_ki0cVQ-Y","title":"شرح نونية ابن القيم(16) -المقدمة(16) -الثلاثاء 8-7-1441هـ","position":15},{"videoId":"a-NdQ8VZNEQ","title":"شرح نونية ابن القيم(17)  -الثلاثاء 30-1-1443هـ","position":16},{"videoId":"Nm1MCVrr_2U","title":"شرح نونية ابن القيم(18) -الثلاثاء 7-2-1443هـ","position":17},{"videoId":"LR8xm4dlzQ0","title":"شرح نونية ابن القيم(19) -الثلاثاء 14-2-1443هـ","position":18},{"videoId":"itlbJ6WHkgU","title":"شرح نونية ابن القيم(20) -الثلاثاء 21-2-1443هـ","position":19},{"videoId":"-UBjSIj1GFk","title":"شرح نونية ابن القيم(21) -الثلاثاء 28-2-1443هـ","position":20},{"videoId":"scoogga2lAg","title":"شرح نونية ابن القيم(22) -الثلاثاء 6-3-1443هـ","position":21},{"videoId":"tSKFxYB4W3Q","title":"شرح نونية ابن القيم(23) -الثلاثاء 20-3-1443هـ","position":22},{"videoId":"x5Emv6IsQR8","title":"شرح نونية ابن القيم(24) -الثلاثاء 27-3-1443هـ","position":23},{"videoId":"fpsmNFQxCuk","title":"شرح نونية ابن القيم(25) -الثلاثاء 4-4-1443هـ","position":24},{"videoId":"jWS_7B54Ncw","title":"شرح نونية ابن القيم(26) -الثلاثاء 11-4-1443هـ","position":25},{"videoId":"QRhrkU3IZKU","title":"شرح نونية ابن القيم(27) -الثلاثاء 29-6-1443هـ","position":26},{"videoId":"-Ouhr4cU7NA","title":"شرح نونية ابن القيم(28) -الثلاثاء 7-7-1443هـ","position":27},{"videoId":"HcUd7uEG_Lk","title":"شرح نونية ابن القيم(29) -الثلاثاء 14-7-1443هـ","position":28},{"videoId":"K02HIT6le5U","title":"شرح نونية ابن القيم(30) -الثلاثاء 28-7-1443هـ","position":29},{"videoId":"xhwcVYltM6Y","title":"شرح نونية ابن القيم(31) -الثلاثاء 5-8-1443هـ","position":30},{"videoId":"khOHB6i5YjI","title":"شرح نونية ابن القيم(32) -الثلاثاء 19-8-1443هـ","position":31},{"videoId":"Q7ZC-fQClEg","title":"شرح نونية ابن القيم(33) -الثلاثاء 26-8-1443هـ","position":32},{"videoId":"96JhzZWpazc","title":"شرح نونية ابن القيم(34) -الثلاثاء 10-2-1444هـ","position":33},{"videoId":"002NG6oWG4I","title":"شرح نونية ابن القيم(35) -الثلاثاء 17-2-1444هـ","position":34},{"videoId":"mx_QxmAc_7o","title":"شرح نونية ابن القيم(36) -الثلاثاء 24-2-1444هـ","position":35},{"videoId":"0Q_sXPOM2b8","title":"شرح نونية ابن القيم(37) -الثلاثاء 1-3-1444هـ","position":36},{"videoId":"LdPRsUFhTmU","title":"شرح نونية ابن القيم(38) -الثلاثاء 8-3-1444هـ","position":37},{"videoId":"g6csnE4WtL4","title":"شرح نونية ابن القيم(39) -الثلاثاء 15-3-1444هـ","position":38},{"videoId":"byYqXu8u4JY","title":"شرح نونية ابن القيم(40) -الثلاثاء 29-3-1444هـ","position":39},{"videoId":"F3ngwykJC7s","title":"شرح نونية ابن القيم(41) -الثلاثاء 7-4-1444هـ","position":40},{"videoId":"2oPRnXxwrTA","title":"شرح نونية ابن القيم(42) -الثلاثاء 19-5-1444هـ","position":41},{"videoId":"ZqWQtqdFbM0","title":"شرح نونية ابن القيم(43) -الثلاثاء 26-5-1444هـ","position":42},{"videoId":"DEelB1xPxX0","title":"شرح نونية ابن القيم(44) -الثلاثاء 3-6-1444هـ","position":43},{"videoId":"wotulYFCN4U","title":"شرح نونية ابن القيم(45) -الثلاثاء 10-6-1444هـ","position":44},{"videoId":"ZSfnOybZxKI","title":"شرح نونية ابن القيم(46) -الثلاثاء 17-6-1444هـ","position":45},{"videoId":"IaQ2ef7VeVM","title":"شرح نونية ابن القيم(47) -الثلاثاء 2-7-1444هـ","position":46},{"videoId":"Y4DMLPdmYuQ","title":"شرح نونية ابن القيم(48) -الثلاثاء 9-7-1444هـ","position":47},{"videoId":"zLz3dKOKpW0","title":"شرح نونية ابن القيم(49) -الثلاثاء 16-7-1444هـ","position":48},{"videoId":"lXysHj8Mols","title":"شرح نونية ابن القيم(50) -الثلاثاء 13-2-1445هـ","position":49},{"videoId":"ihLzyXlWauI","title":"شرح نونية ابن القيم(51) -الثلاثاء 27-2-1445هـ","position":50},{"videoId":"pzFyjAB5chE","title":"شرح نونية ابن القيم(52) -الثلاثاء 4-3-1445هـ","position":51},{"videoId":"4T6d7BbtYR8","title":"شرح نونية ابن القيم(53) -الثلاثاء 11-3-1445هـ","position":52},{"videoId":"c-q2uLbqXBg","title":"شرح نونية ابن القيم(54) -الثلاثاء 25-3-1445هـ","position":53},{"videoId":"DvxTBAtyFh8","title":"شرح نونية ابن القيم(55) -الثلاثاء 21-5-1445هـ","position":54},{"videoId":"XD_eXVTdEtY","title":"شرح نونية ابن القيم(56) -الثلاثاء 6-6-1445هـ","position":55},{"videoId":"NC7qc8QzcyY","title":"شرح نونية ابن القيم(57) -الثلاثاء 13-6-1445هـ","position":56},{"videoId":"U_N6U7ti0WQ","title":"شرح نونية ابن القيم (58) -الثلاثاء 11-7-1445هـ","position":57},{"videoId":"FuQwTH3aIt0","title":"شرح نونية ابن القيم(60) -الثلاثاء 23-2-1446هـ","position":58},{"videoId":"nhSiXCW6sLw","title":"شرح نونية ابن القيم(61) -الثلاثاء 30-2-1446هـ","position":59},{"videoId":"J_uyc61a0AI","title":"شرح نونية ابن القيم(62) -الثلاثاء 7-3-1446هـ","position":60},{"videoId":"Lc4sAEk8onY","title":"شرح نونية ابن القيم(63) -الثلاثاء 14-3-1446هـ","position":61},{"videoId":"yM9UTGRwhzg","title":"شرح نونية ابن القيم(64) -الثلاثاء 28-3-1446هـ","position":62},{"videoId":"ar_iFrkaaqo","title":"شرح نونية ابن القيم(65) -الثلاثاء 5-4-1446هـ","position":63},{"videoId":"zB3xC0kEpnc","title":"شرح نونية ابن القيم(66) -الثلاثاء 24-5-1446هـ","position":64},{"videoId":"5uVwXEeUJh8","title":"شرح نونية ابن القيم(67) -الثلاثاء 2-6-1446هـ","position":65},{"videoId":"JEMA1EjOwWg","title":"شرح نونية ابن القيم(68) -الثلاثاء 16-6-1446هـ","position":66},{"videoId":"iGlNfKMsD8Q","title":"شرح نونية ابن القيم(69) -الثلاثاء 23-6-1446هـ","position":67},{"videoId":"VoIjQeVF70Y","title":"شرح نونية ابن القيم(70) -الثلاثاء 14-7-1446هـ","position":68},{"videoId":"dCWvNgdH-94","title":"شرح نونية ابن القيم(71) -الثلاثاء 21-7-1446هـ","position":69},{"videoId":"5amAHpblijA","title":"شرح نونية ابن القيم(72) -الثلاثاء 28-7-1446هـ","position":70}]