[{"videoId":"PGvrrb84g94","title":"1451 - 1652 باب   النهي عن طلب الإمارة    1📔 صحيح مسلم - ابن عثيمين","position":0},{"videoId":"cQTLf1M5tZ8","title":"1452 - 1652 باب   كراهة الإمارة  بغير ضرورة  حديث يا أبا ذر إنك ضعيف...📔 صحيح مسلم - ابن عثيمين","position":1},{"videoId":"7o14kd6dJPM","title":"1453 - 1652 باب   فضيلة الإمام العادل، وعقوبة الجائر، والحث على الرفق...📔 صحيح مسلم - ابن عثيمين","position":2},{"videoId":"w-0dbNSnzcA","title":"1454 - 1652 باب   فضيلة الإمام العادل، وعقوبة الجائر، والحث على الرفق...📔 صحيح مسلم - ابن عثيمين","position":3},{"videoId":"yLfqtPvXc88","title":"1455 - 1652 باب   فضيلة الإمام العادل، وعقوبة الجائر، والحث على الرفق...📔 صحيح مسلم - ابن عثيمين","position":4},{"videoId":"EtYOPY6nguk","title":"1456 - 1652 باب   فضيلة الإمام العادل، وعقوبة الجائر، والحث على الرفق...📔 صحيح مسلم - ابن عثيمين","position":5},{"videoId":"pFYfqMMTMMc","title":"1457 - 1652 باب   غلظ تحريم الغلول  حديث لا ألفين أحدكم  يجيء يوم القيامة...📔 صحيح مسلم - ابن عثيمين","position":6},{"videoId":"ck8w80b2En8","title":"1458 - 1652 باب   تحريم هدايا  العمال  حديث   استعمل رسول الله رجلا...📔 صحيح مسلم - ابن عثيمين","position":7},{"videoId":"HeknXStWuM0","title":"1459 - 1652 باب   تحريم هدايا  العمال  حديث   استعمل رسول الله رجلا من...📔 صحيح مسلم - ابن عثيمين","position":8},{"videoId":"etq2Y3SC3qs","title":"1460 - 1652 باب    وجوب طاعة الامراء في غير معصية     1   شرح حديث...📔 صحيح مسلم - ابن عثيمين","position":9},{"videoId":"RVnJlFn72tU","title":"1461 - 1652 باب    وجوب طاعة الامراء في غير معصية     2📔 صحيح مسلم - ابن عثيمين","position":10},{"videoId":"Gq30VE7enmw","title":"1462 - 1652 باب    وجوب طاعة الامراء في غير معصية    3  إجابة عن بعض...📔 صحيح مسلم - ابن عثيمين","position":11},{"videoId":"cm1okBBwqHw","title":"1463 - 1652 باب    وجوب طاعة الامراء في غير معصية     4📔 صحيح مسلم - ابن عثيمين","position":12},{"videoId":"cMqSCMMsqK0","title":"1464 - 1652 باب    وجوب طاعة الامراء في غير معصية     5📔 صحيح مسلم - ابن عثيمين","position":13},{"videoId":"GSIehwlFpaw","title":"1465 - 1652 باب    وجوب طاعة الامراء في غير معصية     6📔 صحيح مسلم - ابن عثيمين","position":14},{"videoId":"P3xOSmriokU","title":"1466 - 1652 باب    وجوب طاعة الامراء في غير معصية    7 حديث    بايعنا...📔 صحيح مسلم - ابن عثيمين","position":15},{"videoId":"tSLh3EcQv_g","title":"1467 - 1652 باب    وجوب طاعة الامراء في غير معصية    8 حديث    بايعنا...📔 صحيح مسلم - ابن عثيمين","position":16},{"videoId":"R2NbVAiyNLg","title":"1468 - 1652 باب    وجوب طاعة الامراء في غير معصية    9إجابة أسئلة📔 صحيح مسلم - ابن عثيمين","position":17},{"videoId":"x4uGhP95ANw","title":"1469 - 1652 باب   الإمام جنة يقاتل به من وراءه  ويتقى به📔 صحيح مسلم - ابن عثيمين","position":18},{"videoId":"jIzgG-WpDGA","title":"1470 - 1652 باب   وجوب الوفاء ببيعة  الخلفاءالأول فالأول    1   حديث كانت...📔 صحيح مسلم - ابن عثيمين","position":19},{"videoId":"AWJaBoSev0w","title":"1471 - 1652 باب   وجوب الوفاء ببيعة  الخلفاءالأول فالأول    2   حديث  إنه...📔 صحيح مسلم - ابن عثيمين","position":20},{"videoId":"yDfT5Hsqams","title":"1472 - 1652 باب   وجوب الوفاء ببيعة  الخلفاءالأول فالأول    3   حديث  إنه...📔 صحيح مسلم - ابن عثيمين","position":21},{"videoId":"El-e2m3fXaU","title":"1473 - 1652 باب الأمر بالصبر  عند ظلم الولاة  واستئثارهم   حديث  إنكم...📔 صحيح مسلم - ابن عثيمين","position":22},{"videoId":"2RHv7kLlwXI","title":"1474 - 1652 باب  في طاعة الأمراء  وإن منعوا  الحقوق📔 صحيح مسلم - ابن عثيمين","position":23},{"videoId":"t4GdxpF9Ot0","title":"1475 - 1652 باب  وجوب ملازمة جماعة المسلمين عند ظهور الفتن وفي كل...📔 صحيح مسلم - ابن عثيمين","position":24},{"videoId":"RDbuFeNw-uQ","title":"1476 - 1652 باب  وجوب ملازمة جماعة المسلمين عند ظهور الفتن وفي كل...📔 صحيح مسلم - ابن عثيمين","position":25},{"videoId":"fL9fqARrqgw","title":"1477 - 1652 باب  وجوب ملازمة جماعة المسلمين عند ظهور الفتن وفي كل حال...📔 صحيح مسلم - ابن عثيمين","position":26},{"videoId":"KRlzOkbt8CY","title":"1478 - 1652 باب  وجوب ملازمة جماعة المسلمين عند ظهور الفتن وفي كل...📔 صحيح مسلم - ابن عثيمين","position":27},{"videoId":"Z3Vp1TTGr38","title":"1479 - 1652 باب   حكم من فرق أمر المسلمين وهو مجتمع  حديث من أتاكم...📔 صحيح مسلم - ابن عثيمين","position":28},{"videoId":"s0rRgNYswew","title":"1480 - 1652 باب إذا بويع لخليفتين حديث إذا بويع لخليفتين فاقتلوا الآخر منهما📔 صحيح مسلم - ابن عثيمين","position":29},{"videoId":"KHZb8ZzhDS0","title":"1481 - 1652 باب وجوب الإنكار على الأمراء  فيما يخالف الشرع وترك قتالهم ما...📔 صحيح مسلم - ابن عثيمين","position":30},{"videoId":"HWDlg167f8E","title":"1482 - 1652 باب  خيار الأئمة وشرارهم، حديث خيار ائمتكم الذين تحبونهم...📔 صحيح مسلم - ابن عثيمين","position":31},{"videoId":"lqbvJp4gM3k","title":"1483 - 1652 باب  استحباب  مبايعة الإمام الجيش عند ارادة القتال وبيان بيعة...📔 صحيح مسلم - ابن عثيمين","position":32},{"videoId":"5s9AWTbni1I","title":"1484 - 1652 باب  استحباب  مبايعة الإمام الجيش عند ارادة القتال وبيان بيعة...📔 صحيح مسلم - ابن عثيمين","position":33},{"videoId":"wIpHYMbID3E","title":"1485 - 1652 باب  تحريم رجوع المهاجر لى استيطان وطنه📔 صحيح مسلم - ابن عثيمين","position":34},{"videoId":"JxMOEUYXnWs","title":"1486 - 1652 باب المبايعة بعد فتح مكة على الاسلام والجهاد والخير وبيان ...📔 صحيح مسلم - ابن عثيمين","position":35},{"videoId":"6XJNhULv55c","title":"1487 - 1652 باب   كيفية بيعة النساء ، وحديث ما مس رسول الله بيده امرأة قط📔 صحيح مسلم - ابن عثيمين","position":36},{"videoId":"Q6iVFLZhd3k","title":"1488 - 1652 باب    البيعة على السمع والطاعة فيما استطاع📔 صحيح مسلم - ابن عثيمين","position":37},{"videoId":"17UDAMXIWR0","title":"1489 - 1652 باب  بيان سن البلوغ ، حديث ابن عمر قال عرضني رسول الله يوم ...📔 صحيح مسلم - ابن عثيمين","position":38},{"videoId":"gDLrQVgNw1A","title":"1490 - 1652 باب   النهي أن يسافر بالمصحف إلى أرض الكفار إذا خيف وقوعه...📔 صحيح مسلم - ابن عثيمين","position":39},{"videoId":"FiodnGxHS1w","title":"1491 - 1652 باب   المسابقة بين الخيل وتضميرها📔 صحيح مسلم - ابن عثيمين","position":40},{"videoId":"OMbPpOWWuv8","title":"1492 - 1652 باب  الخيل  في نواصيها الخير إلى يوم القيامة، حديث ابن عمر أن...📔 صحيح مسلم - ابن عثيمين","position":41},{"videoId":"v-cmy1LU_4w","title":"1493 - 1652 باب  ما يكره من صفات الخيل📔 صحيح مسلم - ابن عثيمين","position":42},{"videoId":"85Fn2vT3utY","title":"1494 - 1652 باب  فضل الجهاد والخروج في سبيل الله   1📔 صحيح مسلم - ابن عثيمين","position":43},{"videoId":"F5qyHss5DGA","title":"1495 - 1652 باب  فضل الجهاد والخروج في سبيل الله   2📔 صحيح مسلم - ابن عثيمين","position":44},{"videoId":"debHNr5ewQw","title":"1496 - 1652 باب  فضل الجهاد والخروج في سبيل الله   3📔 صحيح مسلم - ابن عثيمين","position":45},{"videoId":"i03mu8gYOfU","title":"1497 - 1652 باب  فضل الشهادة في سبيل الله📔 صحيح مسلم - ابن عثيمين","position":46},{"videoId":"FacZP8V1eZs","title":"1498 - 1652 باب فضل الغدوة والروحة في سبيل الله،  حديث لغدوة أو روحة...📔 صحيح مسلم - ابن عثيمين","position":47},{"videoId":"J6fc_JKzWrw","title":"1499 - 1652 باب  بيان ما أعده الله تعالى للمجاهد في سبيل الله من الدرجات...📔 صحيح مسلم - ابن عثيمين","position":48},{"videoId":"QqEFg6X-miA","title":"1500 - 1652 باب  من قتل في سبيل الله كفرت خطاياه، إلا الدين📔 صحيح مسلم - ابن عثيمين","position":49},{"videoId":"a0j9l5VZJb8","title":"1501 - 1652 باب  بيان أن أرواح الشهداء في الجنة، وأنهم أحياء عند ربهم يرزقون📔 صحيح مسلم - ابن عثيمين","position":50},{"videoId":"dXFp2j_d5Yg","title":"1502 - 1652 باب    فضل الجهاد والرباط📔 صحيح مسلم - ابن عثيمين","position":51},{"videoId":"5MYTmDpCnso","title":"1503 - 1652 باب  بيان الرجل يقتل أحدهما الآخر ،يدخلان الجنة، حديث يضحك...📔 صحيح مسلم - ابن عثيمين","position":52},{"videoId":"do-443f9P_s","title":"1504 - 1652 باب من قتل كافرا ثم سدد، حديث لا يجتمع كافر وقاتله في النار أبدا📔 صحيح مسلم - ابن عثيمين","position":53},{"videoId":"w0LkEjBM3EU","title":"1505 - 1652 باب   فضل الصدقة في سبيل الله وتضعيفها📔 صحيح مسلم - ابن عثيمين","position":54},{"videoId":"ryY5T5I8_Ls","title":"1506 - 1652 باب  فضل إعانة الغازي في سبيل الله بمركوب وغيره، وخلافته في...📔 صحيح مسلم - ابن عثيمين","position":55},{"videoId":"dto1-ZAylQU","title":"1507 - 1652 باب  فضل إعانة الغازي في سبيل الله بمركوب وغيره، وخلافته في...📔 صحيح مسلم - ابن عثيمين","position":56},{"videoId":"leBxcV1sfaI","title":"1508 - 1652 باب  حرمة نساء المجاهدين، وإثم من خانهم فيهن،  حديثحرمة...📔 صحيح مسلم - ابن عثيمين","position":57},{"videoId":"xPLURNn4elU","title":"1509 - 1652 باب    سقوط فرض الجهاد عن المعذورين📔 صحيح مسلم - ابن عثيمين","position":58},{"videoId":"_5F185bb1gI","title":"1510 - 1652 باب  ثبوت الجنة للشهيد  1📔 صحيح مسلم - ابن عثيمين","position":59},{"videoId":"bcKUCSZvWSc","title":"1511 - 1652 باب  ثبوت الجنة للشهيد  2📔 صحيح مسلم - ابن عثيمين","position":60},{"videoId":"vYDyCNriNRA","title":"1512 - 1652 باب   من قاتل لتكون كلمة الله هي العليا فهو في سبيل الله📔 صحيح مسلم - ابن عثيمين","position":61},{"videoId":"Jt7ThAV_fqo","title":"1513 - 1652 باب   من قاتل  للرياء والسمعة استحق النار، حديث  إن أول الناس...📔 صحيح مسلم - ابن عثيمين","position":62},{"videoId":"A5bj_zt_W14","title":"1514 - 1652 باب  بيان قدر ثواب من غزا فغنم ومن لم يغنم، حديث  من من غازية...📔 صحيح مسلم - ابن عثيمين","position":63},{"videoId":"9UCywksu2Ak","title":"1515 - 1652 باب قوله صلى الله عليه وسلم إنما الأعمال بالنية وإنما لكل ...📔 صحيح مسلم - ابن عثيمين","position":64},{"videoId":"DTtTXyRXzP4","title":"1516 - 1652 باب استحباب طلب الشهادة في سبيل الله تعالىن  حديث...📔 صحيح مسلم - ابن عثيمين","position":65},{"videoId":"EYz3CEunSek","title":"1517 - 1652 باب  من مات ولم يغزو ولم يحدث نفسه بالغزو، عن أبي هريرة أن...📔 صحيح مسلم - ابن عثيمين","position":66},{"videoId":"qDyTH_iZkCs","title":"1518 - 1652 باب   ثواب من حبسه عن الغزو مرض، حديث  إن بالمدينة لرجالا ...📔 صحيح مسلم - ابن عثيمين","position":67},{"videoId":"QV2jtZc70eg","title":"1519 - 1652 باب  فضل الغزو في البحر، حديث  عن أنس بن مالك أن رسول الله...📔 صحيح مسلم - ابن عثيمين","position":68},{"videoId":"fFzDDq1sywo","title":"1520 - 1652 باب  فضل الغزو في البحر، حديث  عن أنس بن مالك أن رسول الله...📔 صحيح مسلم - ابن عثيمين","position":69},{"videoId":"HsWLXFR0IS8","title":"1521 - 1652 باب فضل الرباط في سبيل الله ، عن سلمان رضي الله عنه قال...📔 صحيح مسلم - ابن عثيمين","position":70},{"videoId":"Q9kDfgzgytE","title":"1522 - 1652 باب   بيان الشهداء، عن أبي هريرة أن رسول الله صلى الله عليه...📔 صحيح مسلم - ابن عثيمين","position":71},{"videoId":"roAByRc4ICk","title":"1523 - 1652 باب بيان الشهداء عن أبي هريرة أن رسول الله صلى الله عليه وسلم...📔 صحيح مسلم - ابن عثيمين","position":72},{"videoId":"XMZTIAAdCrk","title":"1524 - 1652 باب  فضل الرمي والحث عليه ،  حديث ألا إن القوة الرمي، ألا إن...📔 صحيح مسلم - ابن عثيمين","position":73},{"videoId":"7OV7o91vPyI","title":"1525 - 1652 باب   قوله صلى الله عليه وسلم لا تزال طائفة من أمتي ظاهرين...📔 صحيح مسلم - ابن عثيمين","position":74}]