[{"videoId":"ARmSp7apE6k","title":"1 - 12 - مختصر فقه العبادات - الدرس الأول - الشيخ محمد بن صالح العثيمين","position":0},{"videoId":"KsIDiJF_20M","title":"2 - 12 - مختصر فقه العبادات - الدرس الثاني - الشيخ محمد بن صالح العثيمين","position":1},{"videoId":"De2Ec4Zu054","title":"3 - 12 - مختصر فقه العبادات - الدرس الثالث - الشيخ محمد بن صالح العثيمين","position":2},{"videoId":"GkHXpR4ZuDA","title":"4 - 12 - مختصر فقه العبادات - الدرس الرابع - الشيخ محمد بن صالح العثيمين","position":3},{"videoId":"k572RUQtQLc","title":"5 - 12 - مختصر فقه العبادات - الدرس الخامس - الشيخ محمد بن صالح العثيمين","position":4},{"videoId":"t-OQMnrRYGg","title":"6 - 12 - مختصر فقه العبادات - الدرس السادس - الشيخ محمد بن صالح العثيمين","position":5},{"videoId":"Yu63Cy3oxxo","title":"7 - 12 - مختصر فقه العبادات - الدرس السابع - الشيخ محمد بن صالح العثيمين","position":6},{"videoId":"VKVgwV1Gct8","title":"8 - 12 - مختصر فقه العبادات - الدرس الثامن - الشيخ محمد بن صالح العثيمين","position":7},{"videoId":"TNIwySdxtio","title":"9 - 12 - مختصر فقه العبادات - الدرس التاسع - الشيخ محمد بن صالح العثيمين","position":8},{"videoId":"SRgKzL9l-pU","title":"10 - 12 - مختصر فقه العبادات - الدرس العاشر - الشيخ محمد بن صالح العثيمين","position":9},{"videoId":"-rLap4-fI08","title":"11 - 12 - مختصر فقه العبادات - الدرس الحادي عشر - الشيخ محمد بن صالح العثيمين","position":10},{"videoId":"o7xTNyk35d8","title":"12 - 12 - مختصر فقه العبادات - الدرس الثاني عشر - الشيخ محمد بن صالح العثيمين","position":11}]